pyspimosim/__init__.py
pyspimosim/__main__.py
pyspimosim/base_model.py
pyspimosim/csv_pipe_model.py
pyspimosim/main.py
pyspimosim/model_loader.py
pyspimosim/protocol.py
pyspimosim/server_simulation_backend.py
pyspimosim/servers.py
pyspimosim/models/ising_model.py
pyspimosim/models/two_col_csv_model.py
pyspimosim/models/www_model.py
pyspimosim/spimosim/LICENSE.md
pyspimosim/spimosim/README.md
pyspimosim/spimosim/index.html
pyspimosim/spimosim/dsmc/README.txt
pyspimosim/spimosim/dsmc/index.html
pyspimosim/spimosim/dsmc/index.php~
pyspimosim/spimosim/dsmc/model-config.js
pyspimosim/spimosim/dsmc/model-info.html
pyspimosim/spimosim/dsmc/model.js
pyspimosim/spimosim/dsmc/particle-video.js
pyspimosim/spimosim/dsmc/plots/data-aggregators.js
pyspimosim/spimosim/dsmc/plots/plot-computers.js
pyspimosim/spimosim/dsmc/plots/plot-displays.js
pyspimosim/spimosim/ext_lib/css/radio-checkbox.css
pyspimosim/spimosim/ext_lib/css/sliders.css
pyspimosim/spimosim/ext_lib/lib/codemirror/AUTHORS
pyspimosim/spimosim/ext_lib/lib/codemirror/LICENSE
pyspimosim/spimosim/ext_lib/lib/codemirror/ambiance.min.css
pyspimosim/spimosim/ext_lib/lib/codemirror/codemirror.min.css
pyspimosim/spimosim/ext_lib/lib/codemirror/codemirror.min.js
pyspimosim/spimosim/ext_lib/lib/codemirror/emacs.min.js
pyspimosim/spimosim/ext_lib/lib/codemirror/javascript.min.js
pyspimosim/spimosim/ext_lib/lib/codemirror/sublime.min.js
pyspimosim/spimosim/ext_lib/lib/codemirror/vim.min.js
pyspimosim/spimosim/ext_lib/lib/dygraph/dygraph.min.css
pyspimosim/spimosim/ext_lib/lib/dygraph/dygraph.min.css.map
pyspimosim/spimosim/ext_lib/lib/dygraph/dygraph.min.js
pyspimosim/spimosim/ext_lib/lib/dygraph/dygraph.min.js.map
pyspimosim/spimosim/ext_lib/lib/gif.js/LICENSE
pyspimosim/spimosim/ext_lib/lib/gif.js/gif.js
pyspimosim/spimosim/ext_lib/lib/gif.js/gif.worker.js
pyspimosim/spimosim/ext_lib/lib/jszip/LICENSE.markdown
pyspimosim/spimosim/ext_lib/lib/jszip/jszip.js
pyspimosim/spimosim/ext_lib/lib/modernizr/modernizr-custom.js
pyspimosim-1.2.19.dist-info/ALL_LICENSES.md
pyspimosim-1.2.19.dist-info/LICENSE.md
pyspimosim-1.2.19.dist-info/METADATA
pyspimosim-1.2.19.dist-info/WHEEL
pyspimosim-1.2.19.dist-info/entry_points.txt
pyspimosim-1.2.19.dist-info/top_level.txt
pyspimosim-1.2.19.dist-info/RECORD
