Metadata-Version: 2.2
Name: pyspimosim
Version: 1.2.19
Summary: SpiMoSim
Author: Pascal Grafe
License: # List of licenses and copyright notices
Project-URL: Homepage, http://spimosim.pascalgrafe.net/
Project-URL: Bug Tracker, https://github.com/pasgra/pyspimosim/issues
Classifier: Programming Language :: Python :: 3
Classifier: License :: OSI Approved :: MIT License
Classifier: Operating System :: OS Independent
Requires-Python: >=3.6
License-File: LICENSE.md
License-File: ALL_LICENSES.md
Requires-Dist: argcomplete
Requires-Dist: numpy
Requires-Dist: tornado
Requires-Dist: dataclasses; python_version < "3.7"
